slackfin/__init__.py
slackfin/blocks.py
slackfin/formatter.py
slackfin/message.py
slackfin/types.py
slackfin-0.2.2.dist-info/LICENSE
slackfin-0.2.2.dist-info/METADATA
slackfin-0.2.2.dist-info/WHEEL
slackfin-0.2.2.dist-info/top_level.txt
slackfin-0.2.2.dist-info/RECORD
