Metadata-Version: 2.1
Name: slackfin
Version: 0.2.2
Summary: Python library for generating Slack messages
Home-page: https://github.com/caltechads/slackfin
Author: Glenn W. Bach
License: MIT License
Project-URL: Issues, https://github.com/caltechads/slackfin/issues
Project-URL: CI, https://github.com/caltechads/slackfin/actions
Project-URL: Changelog, https://github.com/caltechads/slackfin/releases
Requires-Python: >=3.7
License-File: LICENSE
Provides-Extra: test
Requires-Dist: pytest ; extra == 'test'
